pytometry/__init__.py
pytometry/io/__init__.py
pytometry/io/_readfcs.py
pytometry/pl/__init__.py
pytometry/pl/_histogram.py
pytometry/pl/_scatter_density.py
pytometry/pp/__init__.py
pytometry/pp/_process_data.py
pytometry/tl/__init__.py
pytometry/tl/_normalization.py
pytometry/tl/clustering/__init__.py
pytometry/tl/clustering/_flowsom.py
pytometry-0.1.6.dist-info/METADATA
pytometry-0.1.6.dist-info/WHEEL
pytometry-0.1.6.dist-info/licenses/LICENSE
pytometry-0.1.6.dist-info/RECORD
