Metadata-Version: 2.3
Name: pytometry
Version: 0.1.6
Summary: Flow & mass cytometry analytics in scverse
Project-URL: Documentation, https://pytometry.readthedocs.io/
Project-URL: Source, https://github.com/scverse/pytometry
Project-URL: Home-page, https://github.com/scverse/pytometry
Author: Maren Büttner
Maintainer: Quentin Blampey
Maintainer-email: Maren Büttner <maren.buettner@tum.de>
License: Apache License
License-File: LICENSE
Requires-Python: >=3.10
Requires-Dist: anndata
Requires-Dist: consensusclustering
Requires-Dist: flowutils
Requires-Dist: matplotlib
Requires-Dist: minisom
Requires-Dist: numba>=0.57
Requires-Dist: numpy>=1.20.0
Requires-Dist: pandas
Requires-Dist: readfcs>=1.1.0
Requires-Dist: scanpy
Requires-Dist: scipy
Requires-Dist: seaborn
Provides-Extra: dev
Requires-Dist: pre-commit; extra == 'dev'
Provides-Extra: doc
Requires-Dist: docutils!=0.18.*,!=0.19.*,>=0.8; extra == 'doc'
Requires-Dist: ipykernel; extra == 'doc'
Requires-Dist: ipython; extra == 'doc'
Requires-Dist: myst-nb>=1.1.0; extra == 'doc'
Requires-Dist: pandas; extra == 'doc'
Requires-Dist: sphinx-autodoc-typehints; extra == 'doc'
Requires-Dist: sphinx-book-theme>=1.0.0; extra == 'doc'
Requires-Dist: sphinx-copybutton; extra == 'doc'
Requires-Dist: sphinx>=4; extra == 'doc'
Requires-Dist: sphinxcontrib-bibtex>=1.0.0; extra == 'doc'
Requires-Dist: sphinxext-opengraph; extra == 'doc'
Provides-Extra: test
Requires-Dist: coverage; extra == 'test'
Requires-Dist: nbproject; extra == 'test'
Requires-Dist: nbproject-test; extra == 'test'
Requires-Dist: pytest; extra == 'test'
